smart_commit/__init__.py
smart_commit/ai_providers.py
smart_commit/cache.py
smart_commit/cli.py
smart_commit/config.py
smart_commit/mcp.py
smart_commit/repository.py
smart_commit/templates.py
smart_commit/utils.py
smart_commit/analyzers/__init__.py
smart_commit/analyzers/commit_splitter.py
smart_commit_ai-0.2.4.dist-info/METADATA
smart_commit_ai-0.2.4.dist-info/WHEEL
smart_commit_ai-0.2.4.dist-info/entry_points.txt
smart_commit_ai-0.2.4.dist-info/licenses/LICENSE
smart_commit_ai-0.2.4.dist-info/RECORD
