Metadata-Version: 2.4
Name: smart-commit-ai
Version: 0.2.4
Summary: 🤖 AI-powered git commit message generator with repository context awareness
Project-URL: Homepage, https://github.com/subhayu99/smart-commit
Project-URL: Documentation, https://github.com/subhayu99/smart-commit#readme
Project-URL: Repository, https://github.com/subhayu99/smart-commit
Project-URL: Bug Tracker, https://github.com/subhayu99/smart-commit/issues
Author-email: Subhayu Kumar Bala <balasubhayu99@gmail.com>
Maintainer-email: Subhayu Kumar Bala <balasubhayu99@gmail.com>
License: MIT License
License-File: LICENSE
Keywords: ai,automation,cli,commit,conventional-commits,developer-tools,git,openai,productivity
Classifier: Development Status :: 4 - Beta
Classifier: Environment :: Console
Classifier: Intended Audience :: Developers
Classifier: License :: OSI Approved :: MIT License
Classifier: Operating System :: OS Independent
Classifier: Programming Language :: Python :: 3
Classifier: Programming Language :: Python :: 3.10
Classifier: Programming Language :: Python :: 3.11
Classifier: Programming Language :: Python :: 3.12
Classifier: Topic :: Software Development :: Libraries :: Python Modules
Classifier: Topic :: Software Development :: Version Control :: Git
Classifier: Topic :: Utilities
Classifier: Typing :: Typed
Requires-Python: >=3.10
Requires-Dist: gitpython>=3.1.0
Requires-Dist: litellm>=1.73.6.post1
Requires-Dist: mcp[cli]>=1.9.1
Requires-Dist: pathspec>=0.11.0
Requires-Dist: pydantic>=2.0.0
Requires-Dist: rich>=13.0.0
Requires-Dist: toml>=0.10.2
Requires-Dist: typer>=0.9.0
Provides-Extra: all
Requires-Dist: black>=23.0.0; extra == 'all'
Requires-Dist: build>=0.10.0; extra == 'all'
Requires-Dist: isort>=5.0.0; extra == 'all'
Requires-Dist: mypy>=1.0.0; extra == 'all'
Requires-Dist: pre-commit>=3.0.0; extra == 'all'
Requires-Dist: pytest-cov>=4.0.0; extra == 'all'
Requires-Dist: pytest>=7.0.0; extra == 'all'
Requires-Dist: twine>=4.0.0; extra == 'all'
Provides-Extra: dev
Requires-Dist: black>=23.0.0; extra == 'dev'
Requires-Dist: build>=0.10.0; extra == 'dev'
Requires-Dist: isort>=5.0.0; extra == 'dev'
Requires-Dist: mypy>=1.0.0; extra == 'dev'
Requires-Dist: pre-commit>=3.0.0; extra == 'dev'
Requires-Dist: pytest-cov>=4.0.0; extra == 'dev'
Requires-Dist: pytest>=7.0.0; extra == 'dev'
Requires-Dist: twine>=4.0.0; extra == 'dev'
